wrktoolbox/__init__.py
wrktoolbox/benchmarks.py
wrktoolbox/logs.py
wrktoolbox/main.py
wrktoolbox/web.py
wrktoolbox/wrkoutput.py
wrktoolbox/commands/__init__.py
wrktoolbox/commands/reports.py
wrktoolbox/commands/run.py
wrktoolbox/goals/__init__.py
wrktoolbox/goals/common.py
wrktoolbox/goals/latency.py
wrktoolbox/plugins/__init__.py
wrktoolbox/plugins/clientip.py
wrktoolbox/reports/__init__.py
wrktoolbox/reports/generation.py
wrktoolbox/reports/writer.py
wrktoolbox/results/__init__.py
wrktoolbox/results/importers/__init__.py
wrktoolbox/results/importers/fs.py
wrktoolbox/stores/__init__.py
wrktoolbox/stores/fs.py
wrk_load_tools-0.0.3.dist-info/LICENSE
wrk_load_tools-0.0.3.dist-info/METADATA
wrk_load_tools-0.0.3.dist-info/WHEEL
wrk_load_tools-0.0.3.dist-info/entry_points.txt
wrk_load_tools-0.0.3.dist-info/top_level.txt
wrk_load_tools-0.0.3.dist-info/RECORD
