Metadata-Version: 2.1
Name: wrk-load-tools
Version: 0.0.3
Summary: A tool to run wrk/wrk2 benchmarks and store their output.
Home-page: https://github.com/kishorekumar-kk/wrktoolbox
Author: Kishore Kumar
Author-email: mailtokishorekumar.s@gmail.com
License: MIT
Keywords: wrk runner benchmarks load performance tests
Platform: UNKNOWN
Classifier: Development Status :: 5 - Production/Stable
Classifier: License :: OSI Approved :: MIT License
Classifier: Programming Language :: Python :: 3
Classifier: Operating System :: Unix
Requires-Dist: pyparsing
Requires-Dist: rocore
Requires-Dist: roconfiguration
Requires-Dist: click
Requires-Dist: certifi
